{
  "_typename" : "TH1I",
  "fUniqueID" : 0,
  "fBits" : 50331656,
  "fName" : "TRB_8000_MsgPerTDC",
  "fTitle" : "TRB_8000 Number of messages per TDC",
  "fLineColor" : 602,
  "fLineStyle" : 1,
  "fLineWidth" : 1,
  "fFillColor" : 0,
  "fFillStyle" : 1001,
  "fMarkerColor" : 1,
  "fMarkerStyle" : 1,
  "fMarkerSize" : 1,
  "fNcells" : 6,
  "fXaxis" : {
    "_typename" : "TAxis",
    "fUniqueID" : 0,
    "fBits" : 50331648,
    "fName" : "xaxis",
    "fTitle" : "tdc",
    "fNdivisions" : 510,
    "fAxisColor" : 1,
    "fLabelColor" : 1,
    "fLabelFont" : 42,
    "fLabelOffset" : 4.999999888e-03,
    "fLabelSize" : 3.500000015e-02,
    "fTickLength" : 2.999999933e-02,
    "fTitleOffset" : 1,
    "fTitleSize" : 3.500000015e-02,
    "fTitleColor" : 1,
    "fTitleFont" : 42,
    "fNbins" : 4,
    "fXmin" : 0,
    "fXmax" : 4,
    "fXbins" : [],
    "fFirst" : 0,
    "fLast" : 0,
    "fBits2" : 0,
    "fTimeDisplay" : false,
    "fTimeFormat" : "",
    "fLabels" : {
      "_typename" : "THashList",
      "name" : "THashList",
      "arr" : [{
        "_typename" : "TObjString",
        "fUniqueID" : 1,
        "fBits" : 50331648,
        "fString" : "2000"
      }, {
        "_typename" : "TObjString",
        "fUniqueID" : 2,
        "fBits" : 50331648,
        "fString" : "2001"
      }, {
        "_typename" : "TObjString",
        "fUniqueID" : 3,
        "fBits" : 50331648,
        "fString" : "2002"
      }, {
        "_typename" : "TObjString",
        "fUniqueID" : 4,
        "fBits" : 50331648,
        "fString" : "2003"
      }],
      "opt" : ["", "", "", ""]
    }
  },
  "fYaxis" : {
    "_typename" : "TAxis",
    "fUniqueID" : 0,
    "fBits" : 50331648,
    "fName" : "yaxis",
    "fTitle" : "",
    "fNdivisions" : 510,
    "fAxisColor" : 1,
    "fLabelColor" : 1,
    "fLabelFont" : 42,
    "fLabelOffset" : 4.999999888e-03,
    "fLabelSize" : 3.500000015e-02,
    "fTickLength" : 2.999999933e-02,
    "fTitleOffset" : 1,
    "fTitleSize" : 3.500000015e-02,
    "fTitleColor" : 1,
    "fTitleFont" : 42,
    "fNbins" : 1,
    "fXmin" : 0,
    "fXmax" : 1,
    "fXbins" : [],
    "fFirst" : 0,
    "fLast" : 0,
    "fBits2" : 0,
    "fTimeDisplay" : false,
    "fTimeFormat" : "",
    "fLabels" : null
  },
  "fZaxis" : {
    "_typename" : "TAxis",
    "fUniqueID" : 0,
    "fBits" : 50331648,
    "fName" : "zaxis",
    "fTitle" : "",
    "fNdivisions" : 510,
    "fAxisColor" : 1,
    "fLabelColor" : 1,
    "fLabelFont" : 42,
    "fLabelOffset" : 4.999999888e-03,
    "fLabelSize" : 3.500000015e-02,
    "fTickLength" : 2.999999933e-02,
    "fTitleOffset" : 1,
    "fTitleSize" : 3.500000015e-02,
    "fTitleColor" : 1,
    "fTitleFont" : 42,
    "fNbins" : 1,
    "fXmin" : 0,
    "fXmax" : 1,
    "fXbins" : [],
    "fFirst" : 0,
    "fLast" : 0,
    "fBits2" : 0,
    "fTimeDisplay" : false,
    "fTimeFormat" : "",
    "fLabels" : null
  },
  "fBarOffset" : 0,
  "fBarWidth" : 1000,
  "fEntries" : 35044,
  "fTsumw" : 1510727,
  "fTsumw2" : 73579547,
  "fTsumwx" : 2275902,
  "fTsumwx2" : 5339612,
  "fMaximum" : -1111,
  "fMinimum" : -1111,
  "fNormFactor" : 0,
  "fContour" : [],
  "fSumw2" : [],
  "fOption" : "",
  "fFunctions" : {
    "_typename" : "TList",
    "name" : "TList",
    "arr" : [],
    "opt" : []
  },
  "fBufferSize" : 0,
  "fBuffer" : [],
  "fBinStatErrOpt" : 0,
  "fArray" : [0, 376410, 383002, 361045, 390270, 0]
}